README.rst
setup.cfg
setup.py
restea/__init__.py
restea/errors.py
restea/fields.py
restea/formats.py
restea/resource.py
restea.egg-info/PKG-INFO
restea.egg-info/SOURCES.txt
restea.egg-info/dependency_links.txt
restea.egg-info/requires.txt
restea.egg-info/top_level.txt
restea/adapters/__init__.py
restea/adapters/base.py
restea/adapters/djangowrap.py
restea/adapters/flaskwrap.py
restea/adapters/wheezywebwrap.py