Metadata-Version: 1.1
Name: restea
Version: 0.3.3
Summary: Simple RESTful server toolkit
Home-page: https://github.com/bodbdigr/restea
Author: Walery Jadlowski
Author-email: bodb.digr@gmail.com
License: MIT
Keywords: rest,restful,restea
Platform: UNKNOWN
Classifier: Development Status :: 5 - Production/Stable
Classifier: Environment :: Web Environment
Classifier: Intended Audience :: Developers
Classifier: License :: OSI Approved :: MIT License
Classifier: Operating System :: OS Independent
Classifier: Programming Language :: Python
Classifier: Programming Language :: Python :: 2.7
Classifier: Programming Language :: Python :: Implementation :: CPython
Classifier: Programming Language :: Python :: Implementation :: PyPy
Classifier: Topic :: Internet :: WWW/HTTP
